pypeln/__init__.py
pypeln/process/__init__.py
pypeln/process/api/concat.py
pypeln/process/api/concat_process_test.py
pypeln/process/api/each.py
pypeln/process/api/each_process_test.py
pypeln/process/api/filter.py
pypeln/process/api/filter_process_test.py
pypeln/process/api/flat_map.py
pypeln/process/api/flat_map_process_test.py
pypeln/process/api/from_iterable.py
pypeln/process/api/from_iterable_process_test.py
pypeln/process/api/map.py
pypeln/process/api/map_process_test.py
pypeln/process/api/ordered.py
pypeln/process/api/ordered_process_test.py
pypeln/process/api/run.py
pypeln/process/api/to_iterable.py
pypeln/process/api/to_iterable_process_test.py
pypeln/process/api/to_stage.py
pypeln/process/queue.py
pypeln/process/queue_process_test.py
pypeln/process/stage.py
pypeln/process/supervisor.py
pypeln/process/supervisor_process_test.py
pypeln/process/utils.py
pypeln/process/worker.py
pypeln/process/worker_process_test.py
pypeln/sync/__init__.py
pypeln/sync/api/concat.py
pypeln/sync/api/concat_sync_test.py
pypeln/sync/api/each.py
pypeln/sync/api/each_sync_test.py
pypeln/sync/api/filter.py
pypeln/sync/api/filter_sync_test.py
pypeln/sync/api/flat_map.py
pypeln/sync/api/flat_map_sync_test.py
pypeln/sync/api/from_iterable.py
pypeln/sync/api/from_iterable_sync_test.py
pypeln/sync/api/map.py
pypeln/sync/api/map_sync_test.py
pypeln/sync/api/ordered.py
pypeln/sync/api/ordered_sync_test.py
pypeln/sync/api/run.py
pypeln/sync/api/to_iterable.py
pypeln/sync/api/to_iterable_sync_test.py
pypeln/sync/api/to_stage.py
pypeln/sync/stage.py
pypeln/sync/utils.py
pypeln/task/__init__.py
pypeln/task/api/concat.py
pypeln/task/api/concat_task_test.py
pypeln/task/api/each.py
pypeln/task/api/each_task_test.py
pypeln/task/api/filter.py
pypeln/task/api/filter_task_test.py
pypeln/task/api/flat_map.py
pypeln/task/api/flat_map_task_test.py
pypeln/task/api/from_iterable.py
pypeln/task/api/from_iterable_task_test.py
pypeln/task/api/map.py
pypeln/task/api/map_task_test.py
pypeln/task/api/ordered.py
pypeln-0.4.9.dist-info/LICENSE
pypeln-0.4.9.dist-info/WHEEL
pypeln-0.4.9.dist-info/METADATA
pypeln-0.4.9.dist-info/RECORD
