Metadata-Version: 2.1
Name: pypeln
Version: 0.4.9
Summary: 
Home-page: https://cgarciae.github.io/pypeln
License: MIT
Author: Cristian Garcia
Author-email: cgarcia.e88@gmail.com
Requires-Python: >=3.6.2,<4.0
Classifier: License :: OSI Approved :: MIT License
Classifier: Programming Language :: Python :: 3
Classifier: Programming Language :: Python :: 3.10
Classifier: Programming Language :: Python :: 3.7
Classifier: Programming Language :: Python :: 3.8
Classifier: Programming Language :: Python :: 3.9
Requires-Dist: dataclasses (>=0.7,<0.8); python_version >= "3.6" and python_version < "3.7"
Requires-Dist: stopit (>=1.1.2,<2.0.0)
Requires-Dist: typing_extensions (>=3.7.4,<4.0.0); python_version < "3.8"
Project-URL: Repository, https://github.com/cgarciae/pypeln
